r4ven_utils/__init__.py
r4ven_utils/log4me.py
r4ven_utils-0.1.1.dist-info/LICENSE
r4ven_utils-0.1.1.dist-info/METADATA
r4ven_utils-0.1.1.dist-info/WHEEL
r4ven_utils-0.1.1.dist-info/top_level.txt
r4ven_utils-0.1.1.dist-info/RECORD
