Metadata-Version: 2.2
Name: r4ven_utils
Version: 0.1.1
Summary: The companion that holds your grab-bag of utility functions and objects
Home-page: https://github.com/VictorFantucci/r4ven_utils_dev
Author: Victor Vinci Fantucci
Author-email: victor.v.fantucci@gmail.com
License: GPLv3
Project-URL: Bug Tracker, https://github.com/VictorFantucci/r4ven_utils_dev/issues
Project-URL: Download, https://github.com/VictorFantucci/r4ven_utils/releases/tag/alpha
Keywords: r4ven_utils,utils,logs
Classifier: Development Status :: 4 - Beta
Classifier: Intended Audience :: Developers
Classifier: Topic :: Software Development :: Documentation
Classifier: License :: OSI Approved :: GNU General Public License v3 (GPLv3)
Classifier: Programming Language :: Python :: 3
License-File: LICENSE
Dynamic: author
Dynamic: author-email
Dynamic: classifier
Dynamic: description
Dynamic: description-content-type
Dynamic: home-page
Dynamic: keywords
Dynamic: license
Dynamic: project-url
Dynamic: summary
